mimir_api/__init__.py
mimir_api/client.py
mimir_api/repositories.py
mimir_api/tools.py
mimir_api/types.py
mimir_api-0.1.5.dist-info/licenses/LICENSE
mimir_api-0.1.5.dist-info/METADATA
mimir_api-0.1.5.dist-info/WHEEL
mimir_api-0.1.5.dist-info/top_level.txt
mimir_api-0.1.5.dist-info/RECORD
